syncro_api
